multivolumefile/__init__.py
multivolumefile/__init__.pyi
multivolumefile/py.typed
multivolumefile/stat.py
multivolumefile-0.2.2.dist-info/LICENSE
multivolumefile-0.2.2.dist-info/METADATA
multivolumefile-0.2.2.dist-info/WHEEL
multivolumefile-0.2.2.dist-info/top_level.txt
multivolumefile-0.2.2.dist-info/RECORD
