Metadata-Version: 2.1
Name: multivolumefile
Version: 0.2.2
Summary: multi volume file wrapper library
Home-page: https://github.com/miurahr/multivolume
Author: Hiroshi Miura
Author-email: miurahr@linux.com
License: LGPL-2.1+
Keywords: multivolume,file
Platform: UNKNOWN
Classifier: Development Status :: 3 - Alpha
Classifier: Environment :: Console
Classifier: License :: OSI Approved :: GNU Lesser General Public License v2 or later (LGPLv2+)
Classifier: Operating System :: MacOS :: MacOS X
Classifier: Operating System :: Microsoft :: Windows
Classifier: Operating System :: POSIX
Classifier: Operating System :: POSIX :: Linux
Classifier: Programming Language :: Python
Classifier: Programming Language :: Python :: 3
Classifier: Programming Language :: Python :: 3.8
Classifier: Programming Language :: Python :: 3 :: Only
Classifier: Topic :: Software Development :: Libraries :: Python Modules
Requires-Python: >=3.6
Provides-Extra: check
Requires-Dist: check-manifest ; extra == 'check'
Requires-Dist: flake8 ; extra == 'check'
Requires-Dist: readme-renderer ; extra == 'check'
Requires-Dist: pygments ; extra == 'check'
Requires-Dist: isort (>=5.0.3) ; extra == 'check'
Requires-Dist: twine ; extra == 'check'
Provides-Extra: test
Requires-Dist: pytest ; extra == 'test'
Requires-Dist: pytest-cov ; extra == 'test'
Requires-Dist: pyannotate ; extra == 'test'
Requires-Dist: coverage[toml] (>=5.2) ; extra == 'test'
Requires-Dist: coveralls (>=2.1.1) ; extra == 'test'
Provides-Extra: type
Requires-Dist: mypy ; extra == 'type'
Requires-Dist: mypy-extensions ; extra == 'type'
